chemistry_llm/__init__.py
chemistry_llm/analysis/ablation_analysis.py
chemistry_llm/analysis/error_analysis.py
chemistry_llm/analysis/metrics.py
chemistry_llm/analysis/statistical_analysis.py
chemistry_llm/analysis/ucq_module.py
chemistry_llm/cli/__init__.py
chemistry_llm/cli/interface.py
chemistry_llm/core/__init__.py
chemistry_llm/core/extractor.py
chemistry_llm/core/model_loader.py
chemistry_llm/core/prompt_builder.py
chemistry_llm/utils/__init__.py
chemistry_llm/utils/device_utils.py
chemistry_llm/utils/logger.py
chemistry_llm/utils/xml_parser.py
rxnextract-1.2.5.dist-info/METADATA
rxnextract-1.2.5.dist-info/WHEEL
rxnextract-1.2.5.dist-info/entry_points.txt
rxnextract-1.2.5.dist-info/top_level.txt
rxnextract-1.2.5.dist-info/RECORD
