Metadata-Version: 2.4
Name: rxnextract
Version: 1.2.5
Summary: Professional chemistry reaction extraction using fine-tuned LLMs
Author-email: ChemPlusX <xyzmadhavi@gmail.com>
License: MIT
Project-URL: Homepage, https://github.com/chemplusx/RxNExtract
Project-URL: Documentation, https://chemplusx.github.io/RxNExtract/
Project-URL: Installation Guide, https://chemplusx.github.io/RxNExtract/INSTALLATION/
Project-URL: Usage Guide, https://chemplusx.github.io/RxNExtract/USAGE/
Project-URL: Analysis, https://chemplusx.github.io/RxNExtract/ANALYSIS/
Project-URL: Changelog, https://chemplusx.github.io/RxNExtract/CHANGELOG/
Project-URL: Bug Reports, https://github.com/chemplusx/RxNExtract/issues
Project-URL: Source, https://github.com/chemplusx/RxNExtract
Keywords: chemistry,reaction,extraction,llm,nlp,machine-learning
Classifier: Development Status :: 5 - Production/Stable
Classifier: Intended Audience :: Science/Research
Classifier: Topic :: Scientific/Engineering :: Chemistry
Classifier: Topic :: Scientific/Engineering :: Artificial Intelligence
Classifier: License :: OSI Approved :: MIT License
Classifier: Programming Language :: Python :: 3
Classifier: Programming Language :: Python :: 3.8
Classifier: Programming Language :: Python :: 3.9
Classifier: Programming Language :: Python :: 3.10
Classifier: Programming Language :: Python :: 3.11
Requires-Python: >=3.8
Requires-Dist: torch>=2.0.0
Requires-Dist: transformers>=4.35.0
Requires-Dist: peft>=0.7.0
Requires-Dist: bitsandbytes>=0.41.0
Requires-Dist: accelerate>=0.24.0
Requires-Dist: numpy>=1.21.0
Requires-Dist: pandas>=1.3.0
Requires-Dist: pyyaml>=6.0
Requires-Dist: tqdm>=4.64.0
Requires-Dist: click>=8.0.0
Provides-Extra: dev
Requires-Dist: pytest>=7.0.0; extra == "dev"
Requires-Dist: pytest-cov>=4.0.0; extra == "dev"
Requires-Dist: black>=23.0.0; extra == "dev"
Requires-Dist: isort>=5.12.0; extra == "dev"
Requires-Dist: flake8>=6.0.0; extra == "dev"
Requires-Dist: mypy>=1.0.0; extra == "dev"
Requires-Dist: pre-commit>=3.0.0; extra == "dev"
Provides-Extra: gpu
Requires-Dist: flash-attn>=2.0.0; extra == "gpu"
Requires-Dist: torch[cuda]>=2.0.0; extra == "gpu"
Requires-Dist: triton>=2.0.0; extra == "gpu"
Provides-Extra: full
Requires-Dist: flash-attn>=2.0.0; extra == "full"
Requires-Dist: wandb>=0.15.0; extra == "full"
Requires-Dist: torch[cuda]>=2.0.0; extra == "full"
Requires-Dist: triton>=2.0.0; extra == "full"
Requires-Dist: jupyter>=1.0.0; extra == "full"
Requires-Dist: matplotlib>=3.5.0; extra == "full"
Requires-Dist: seaborn>=0.11.0; extra == "full"
Requires-Dist: plotly>=5.0.0; extra == "full"
Requires-Dist: scikit-learn>=1.0.0; extra == "full"
